k_hhc.abi3.so
k_hhc-1.0.8.dist-info/RECORD
k_hhc-1.0.8.dist-info/WHEEL
k_hhc-1.0.8.dist-info/top_level.txt
k_hhc-1.0.8.dist-info/METADATA
k_hhc-1.0.8.dist-info/licenses/LICENSE
