Metadata-Version: 2.4
Name: k-hhc
Version: 1.0.8
Summary: Python bindings for Hexahexacontadecimal (base66) encoding
Author: Evan Kirby
License: Apache-2.0
Project-URL: Homepage, https://github.com/kirbyevanj/k-hhc
Project-URL: Repository, https://github.com/kirbyevanj/k-hhc
Project-URL: Issues, https://github.com/kirbyevanj/k-hhc/issues
Keywords: encoding,codec,hhc,hexahexacontadecimal,base66,performance
Classifier: Development Status :: 4 - Beta
Classifier: Intended Audience :: Developers
Classifier: Programming Language :: Python :: 3
Classifier: Programming Language :: Python :: 3.7
Classifier: Programming Language :: Python :: 3.8
Classifier: Programming Language :: Python :: 3.9
Classifier: Programming Language :: Python :: 3.10
Classifier: Programming Language :: Python :: 3.11
Classifier: Programming Language :: Python :: 3.12
Classifier: Programming Language :: Python :: 3.13
Classifier: Programming Language :: C++
Classifier: Operating System :: OS Independent
Classifier: Topic :: Software Development :: Libraries
Requires-Python: >=3.7
License-File: LICENSE
Dynamic: license-file
